{
  "event_id": "ruakaka-2026-07-18-r4",
  "venue": "Ruakaka",
  "race_name": "R4 1600m Mdn",
  "event_name": "Ruakaka (NZL) 18th Jul",
  "race_type": "Flat",
  "start_time_utc": "2026-07-18T02:20:00.000Z",
  "market_id": "1.260074340",
  "market_overround_pct": null,
  "track_condition": null,
  "weather": null,
  "form_analysis": null,
  "runners": [
    {
      "name": "1. Escape Room",
      "saddle_cloth": 1,
      "selection_id": 99429204,
      "status": "ACTIVE",
      "best_back": null,
      "back_depth_aud": 0,
      "bsp_near": null,
      "market_signal": "NEUTRAL",
      "trainer": null,
      "jockey": null,
      "last5": null,
      "career": null,
      "weight_kg": null,
      "barrier": null,
      "form_status": "not_found",
      "warnings": [],
      "last5_parsed": [],
      "data_status": "not_found",
      "open_price": null,
      "call": {
        "call": "NO_CALL",
        "label": "DATA BAD",
        "confidence": null,
        "reason": "data bad: data_status=not_found and no race form on record",
        "guard": "data_adequacy v1.0"
      }
    },
    {
      "name": "2. Fahali",
      "saddle_cloth": 2,
      "selection_id": 100694035,
      "status": "ACTIVE",
      "best_back": null,
      "back_depth_aud": 0,
      "bsp_near": null,
      "market_signal": "NEUTRAL",
      "trainer": null,
      "jockey": null,
      "last5": null,
      "career": null,
      "weight_kg": null,
      "barrier": null,
      "form_status": "not_found",
      "warnings": [],
      "last5_parsed": [],
      "data_status": "not_found",
      "open_price": null,
      "call": {
        "call": "NO_CALL",
        "label": "DATA BAD",
        "confidence": null,
        "reason": "data bad: data_status=not_found and no race form on record",
        "guard": "data_adequacy v1.0"
      }
    },
    {
      "name": "3. Fleetwood",
      "saddle_cloth": 3,
      "selection_id": 55979226,
      "status": "ACTIVE",
      "best_back": null,
      "back_depth_aud": 0,
      "bsp_near": null,
      "market_signal": "NEUTRAL",
      "trainer": null,
      "jockey": null,
      "last5": null,
      "career": null,
      "weight_kg": null,
      "barrier": null,
      "form_status": "not_found",
      "warnings": [],
      "last5_parsed": [],
      "data_status": "not_found",
      "open_price": null,
      "call": {
        "call": "NO_CALL",
        "label": "DATA BAD",
        "confidence": null,
        "reason": "data bad: data_status=not_found and no race form on record",
        "guard": "data_adequacy v1.0"
      }
    },
    {
      "name": "4. Tall Timber",
      "saddle_cloth": 4,
      "selection_id": 100694036,
      "status": "ACTIVE",
      "best_back": null,
      "back_depth_aud": 0,
      "bsp_near": null,
      "market_signal": "NEUTRAL",
      "trainer": null,
      "jockey": null,
      "last5": null,
      "career": null,
      "weight_kg": null,
      "barrier": null,
      "form_status": "not_found",
      "warnings": [],
      "last5_parsed": [],
      "data_status": "not_found",
      "open_price": null,
      "call": {
        "call": "NO_CALL",
        "label": "DATA BAD",
        "confidence": null,
        "reason": "data bad: data_status=not_found and no race form on record",
        "guard": "data_adequacy v1.0"
      }
    },
    {
      "name": "5. Long Island",
      "saddle_cloth": 5,
      "selection_id": 18097068,
      "status": "ACTIVE",
      "best_back": null,
      "back_depth_aud": 0,
      "bsp_near": null,
      "market_signal": "NEUTRAL",
      "trainer": null,
      "jockey": null,
      "last5": null,
      "career": null,
      "weight_kg": null,
      "barrier": null,
      "form_status": "not_found",
      "warnings": [],
      "last5_parsed": [],
      "data_status": "not_found",
      "open_price": null,
      "call": {
        "call": "NO_CALL",
        "label": "DATA BAD",
        "confidence": null,
        "reason": "data bad: data_status=not_found and no race form on record",
        "guard": "data_adequacy v1.0"
      }
    },
    {
      "name": "6. Call Me A Cab",
      "saddle_cloth": 6,
      "selection_id": 100694037,
      "status": "ACTIVE",
      "best_back": null,
      "back_depth_aud": 0,
      "bsp_near": null,
      "market_signal": "NEUTRAL",
      "trainer": null,
      "jockey": null,
      "last5": null,
      "career": null,
      "weight_kg": null,
      "barrier": null,
      "form_status": "not_found",
      "warnings": [],
      "last5_parsed": [],
      "data_status": "not_found",
      "open_price": null,
      "call": {
        "call": "NO_CALL",
        "label": "DATA BAD",
        "confidence": null,
        "reason": "data bad: data_status=not_found and no race form on record",
        "guard": "data_adequacy v1.0"
      }
    },
    {
      "name": "7. The Giggler",
      "saddle_cloth": 7,
      "selection_id": 4196111,
      "status": "ACTIVE",
      "best_back": null,
      "back_depth_aud": 0,
      "bsp_near": null,
      "market_signal": "NEUTRAL",
      "trainer": null,
      "jockey": null,
      "last5": null,
      "career": null,
      "weight_kg": null,
      "barrier": null,
      "form_status": "not_found",
      "warnings": [],
      "last5_parsed": [],
      "data_status": "not_found",
      "open_price": null,
      "call": {
        "call": "NO_CALL",
        "label": "DATA BAD",
        "confidence": null,
        "reason": "data bad: data_status=not_found and no race form on record",
        "guard": "data_adequacy v1.0"
      }
    },
    {
      "name": "8. Cheerful Smile",
      "saddle_cloth": 8,
      "selection_id": 82017863,
      "status": "ACTIVE",
      "best_back": null,
      "back_depth_aud": 0,
      "bsp_near": null,
      "market_signal": "NEUTRAL",
      "trainer": null,
      "jockey": null,
      "last5": null,
      "career": null,
      "weight_kg": null,
      "barrier": null,
      "form_status": "not_found",
      "warnings": [],
      "last5_parsed": [],
      "data_status": "not_found",
      "open_price": null,
      "call": {
        "call": "NO_CALL",
        "label": "DATA BAD",
        "confidence": null,
        "reason": "data bad: data_status=not_found and no race form on record",
        "guard": "data_adequacy v1.0"
      }
    },
    {
      "name": "9. Miss Margot",
      "saddle_cloth": 9,
      "selection_id": 100694038,
      "status": "ACTIVE",
      "best_back": null,
      "back_depth_aud": 0,
      "bsp_near": null,
      "market_signal": "NEUTRAL",
      "trainer": null,
      "jockey": null,
      "last5": null,
      "career": null,
      "weight_kg": null,
      "barrier": null,
      "form_status": "not_found",
      "warnings": [],
      "last5_parsed": [],
      "data_status": "not_found",
      "open_price": null,
      "call": {
        "call": "NO_CALL",
        "label": "DATA BAD",
        "confidence": null,
        "reason": "data bad: data_status=not_found and no race form on record",
        "guard": "data_adequacy v1.0"
      }
    }
  ],
  "last_polled_at": "2026-07-18T01:48:20.988932Z",
  "adequacy_summary": {
    "guard": "data_adequacy v1.0",
    "ok": 0,
    "no_call": 9
  }
}